iam_builder/__init__.py
iam_builder/command_line.py
iam_builder/exceptions.py
iam_builder/iam_builder.py
iam_builder/iam_schema.py
iam_builder/schemas/iam_schema.json
iam_builder/templates.py
iam_builder-4.17.0.dist-info/METADATA
iam_builder-4.17.0.dist-info/WHEEL
iam_builder-4.17.0.dist-info/entry_points.txt
iam_builder-4.17.0.dist-info/RECORD
