Metadata-Version: 2.3
Name: iam_builder
Version: 4.17.0
Summary: A lil python package to generate iam policies
License: MIT
Author: Karik Isichei
Author-email: karik.isichei@digital.justice.gov.uk
Requires-Python: >=3.9,<4.0
Classifier: License :: OSI Approved :: MIT License
Classifier: Programming Language :: Python :: 3
Classifier: Programming Language :: Python :: 3.9
Classifier: Programming Language :: Python :: 3.10
Classifier: Programming Language :: Python :: 3.11
Classifier: Programming Language :: Python :: 3.12
Classifier: Programming Language :: Python :: 3.13
Requires-Dist: PyYAML (>=6.0,<7.0)
Requires-Dist: importlib-resources (>=6.4.5,<7.0.0)
Requires-Dist: jsonschema (>=4.10.0,<5.0.0)
Requires-Dist: parameterized (==0.7.*)
